sdevpy/__init__.py
sdevpy/settings.py
sdevpy/test.py
sdevpy/analytics/americantree.py
sdevpy/analytics/bachelier.py
sdevpy/analytics/black.py
sdevpy/analytics/fbsabr.py
sdevpy/analytics/mcheston.py
sdevpy/analytics/mcsabr.py
sdevpy/analytics/mczabr.py
sdevpy/analytics/sabr.py
sdevpy/cointegration/back_testing.py
sdevpy/cointegration/black_analytics.py
sdevpy/cointegration/coint_trading.py
sdevpy/cointegration/data_io.py
sdevpy/cointegration/implied_vol.py
sdevpy/cointegration/mean_reversion.py
sdevpy/cointegration/model_settings.py
sdevpy/cointegration/plotting.py
sdevpy/cointegration/run_unit_test.py
sdevpy/cointegration/utils.py
sdevpy/llms/ModelConverter.py
sdevpy/llms/attention.py
sdevpy/llms/chat.py
sdevpy/llms/datasets.py
sdevpy/llms/gpt.py
sdevpy/llms/instructions.py
sdevpy/llms/textgen.py
sdevpy/llms/tokenizers.py
sdevpy/llms/training.py
sdevpy/machinelearning/callbacks.py
sdevpy/machinelearning/datasets.py
sdevpy/machinelearning/learningmodel.py
sdevpy/machinelearning/learningschedules.py
sdevpy/machinelearning/topology.py
sdevpy/market/volsurface.py
sdevpy/maths/constants.py
sdevpy/maths/integration.py
sdevpy/maths/interpolation.py
sdevpy/maths/metrics.py
sdevpy/maths/optimization.py
sdevpy/maths/rand.py
sdevpy/maths/regression.py
sdevpy/maths/sets.py
sdevpy/maths/specialfunctions.py
sdevpy/maths/tridiag.py
sdevpy/models/biexp.py
sdevpy/models/impliedvol.py
sdevpy/models/localvol.py
sdevpy/models/localvol_calib.py
sdevpy/models/localvol_factory.py
sdevpy/models/svi.py
sdevpy/models/svivol.py
sdevpy/montecarlo/singlefactormc.py
sdevpy/montecarlo/smoothers.py
sdevpy/pde/forwardpde.py
sdevpy/pde/pdeschemes.py
sdevpy/projects/chat_gpt2.py
sdevpy/projects/datafiles.py
sdevpy/projects/set_limits.py
sdevpy/projects/update_db.py
sdevpy/projects/aad/aad_mc.py
sdevpy/projects/aad/aad_mc_nd.py
sdevpy/projects/raschka/ch2_working_with_text.py
sdevpy/projects/raschka/ch3_coding_attention.py
sdevpy/projects/raschka/ch4_gpt_model.py
sdevpy-1.0.6.dist-info/METADATA
sdevpy-1.0.6.dist-info/WHEEL
sdevpy-1.0.6.dist-info/top_level.txt
sdevpy-1.0.6.dist-info/RECORD
