Metadata-Version: 2.4
Name: sdevpy
Version: 1.0.6
Summary: Python package for Finance
Author-email: Sebastien Gurrieri <sebgur@gmail.com>
Project-URL: Git page, https://github.com/sebgur/SDev.Python
Project-URL: SDev Finance, http://sdev-finance.com/
Classifier: Programming Language :: Python :: 3
Classifier: Operating System :: OS Independent
Requires-Python: >=3.6
Requires-Dist: pandas
Requires-Dist: numpy
